Metadata-Version: 2.4
Name: llm-to-json
Version: 0.0.42
Summary: Tiny wrapper exposing Prompture helpers to convert LLM output into JSON.
Author-email: Juan Denis <juan@vene.co>
License: MIT
Keywords: llm,json,prompt,structured-output
Requires-Python: >=3.10
Requires-Dist: prompture>=0.0.42
